{"cameraMode":{"drawMode":0,"name":"Shaded","section":"Shading Mode"},"sceneLighting":true,"audioPlay":false,"sceneViewState":{"showFog":true,"showMaterialUpdate":false,"showSkybox":true,"showFlares":true,"showImageEffects":true,"showParticleSystems":true},"in2DMode":false,"pivot":{"x":1.5870075225830079,"y":13.866506576538086,"z":-1.627042293548584},"rotation":{"x":-0.2418234646320343,"y":-0.5870760679244995,"z":0.18955278396606446,"w":-0.7489685416221619},"size":21.909944534301759,"orthographic":false}